cilow/__init__.py
cilow/client.py
cilow/errors.py
cilow/models.py
cilow/cli/__init__.py
cilow/cli/agent.py
cilow/cli/animations.py
cilow/cli/app.py
cilow/cli/llm_providers.py
cilow/cli/memory_manager.py
cilow/cli/screens/__init__.py
cilow/cli/screens/chat.py
cilow/cli/screens/projects.py
cilow/cli/screens/settings.py
cilow/cli/widgets/__init__.py
cilow/cli/widgets/chat_input.py
cilow/cli/widgets/logo.py
cilow/cli/widgets/message_list.py
cilow/cli/widgets/state_indicator.py
cilow/cli/widgets/status_bar.py
cilow/integrations/__init__.py
cilow/integrations/langchain/__init__.py
cilow/integrations/langchain/chat_message_history.py
cilow/integrations/langchain/memory.py
cilow/integrations/langchain/utils.py
cilow/mcp/__init__.py
cilow/mcp/server.py
cilow/mcp/tools.py
cilow-0.2.0.dist-info/licenses/LICENSE
cilow-0.2.0.dist-info/METADATA
cilow-0.2.0.dist-info/WHEEL
cilow-0.2.0.dist-info/entry_points.txt
cilow-0.2.0.dist-info/top_level.txt
cilow-0.2.0.dist-info/RECORD
