Metadata-Version: 2.4
Name: cilow
Version: 0.2.0
Summary: Python SDK for Cilow AI Agent Platform - SOTA Memory Layer for AI
Author-email: Cilow Team <team@cilow.ai>
License: MIT
Project-URL: Homepage, https://cilow.ai
Project-URL: Documentation, https://docs.cilow.ai
Project-URL: Repository, https://github.com/cilow-ai/cilow
Project-URL: Changelog, https://github.com/cilow-ai/cilow/blob/main/CHANGELOG.md
Project-URL: Issues, https://github.com/cilow-ai/cilow/issues
Keywords: ai,memory,agents,llm,rag,vector-search,temporal-graph
Classifier: Development Status :: 4 - Beta
Classifier: Intended Audience :: Developers
Classifier: License :: OSI Approved :: MIT License
Classifier: Operating System :: OS Independent
Classifier: Programming Language :: Python :: 3
Classifier: Programming Language :: Python :: 3.9
Classifier: Programming Language :: Python :: 3.10
Classifier: Programming Language :: Python :: 3.11
Classifier: Programming Language :: Python :: 3.12
Classifier: Topic :: Scientific/Engineering :: Artificial Intelligence
Classifier: Topic :: Database
Classifier: Typing :: Typed
Requires-Python: >=3.9
License-File: LICENSE
Requires-Dist: aiohttp>=3.8.0
Requires-Dist: pydantic>=2.0.0
Provides-Extra: dev
Requires-Dist: pytest>=7.0.0; extra == "dev"
Requires-Dist: pytest-asyncio>=0.21.0; extra == "dev"
Requires-Dist: pytest-cov>=4.0.0; extra == "dev"
Requires-Dist: mypy>=1.0.0; extra == "dev"
Requires-Dist: ruff>=0.1.0; extra == "dev"
Provides-Extra: langchain
Requires-Dist: langchain-core>=0.2.0; extra == "langchain"
Provides-Extra: cli
Requires-Dist: rich>=13.0.0; extra == "cli"
Requires-Dist: anthropic>=0.34.0; extra == "cli"
Requires-Dist: openai>=1.0.0; extra == "cli"
Requires-Dist: textual>=0.87.0; extra == "cli"
Provides-Extra: mcp
Requires-Dist: mcp>=0.1.0; extra == "mcp"
Provides-Extra: all
Requires-Dist: cilow[cli,dev,langchain,mcp]; extra == "all"
Dynamic: license-file
